{
  "project": "okx-onchainos-credit",
  "last_updated": "2026-03-11T06:53:48.8466276Z",
  "last_agent": "codex",
  "current_milestone": null,
  "current_task": null,
  "active_milestones": [],
  "completed_milestones": [
    {
      "id": "M1",
      "name": "Foundation & Infrastructure",
      "completed_at": "2026-03-09T18:10:21.281Z"
    },
    {
      "id": "M2",
      "name": "Score Engine",
      "completed_at": "2026-03-10T00:38:39.547Z"
    },
    {
      "id": "M3",
      "name": "x402 + Credential Issuance",
      "completed_at": "2026-03-10T01:00:40.406Z"
    },
    {
      "id": "M4",
      "name": "Web Dashboard",
      "completed_at": "2026-03-10T01:31:11.049Z"
    },
    {
      "id": "M5",
      "name": "Enterprise API",
      "completed_at": "2026-03-10T01:42:13.080Z"
    },
    {
      "id": "M6",
      "name": "MCP Server + CLI",
      "completed_at": "2026-03-10T02:07:33.525Z"
    }
  ],
  "blockers": [],
  "learnings": [],
  "dependency_graph": {
    "M1": {
      "depends_on": [],
      "blocks": ["M2"]
    },
    "M2": {
      "depends_on": ["M1"],
      "blocks": ["M3"]
    },
    "M3": {
      "depends_on": ["M2"],
      "blocks": ["M4", "M5"]
    },
    "M4": {
      "depends_on": ["M3"],
      "blocks": ["M6"]
    },
    "M5": {
      "depends_on": ["M3"],
      "blocks": ["M6"]
    },
    "M6": {
      "depends_on": ["M4", "M5"],
      "blocks": []
    }
  },
  "synced_plans": ["docs/PLAN.md"],
  "agents": [],
  "finish_jobs": []
}
